{
    "01": [
        {
            "title": "Langfristige strategisch planen",
            "example": "z. B. Russland, China",
            "description": "Lorem ipsum dolor sit amet, consetetur sadipscing elitr, sed diam nonumy eirmod tempor invidunt ut labore et dolore magna aliquyam erat, sed diam voluptua. At vero eos et accusam et",
            "storys": []
        },
        {
            "title": "(Wirtschaftlichen) Druck ausüben/spüren",
            "example": "z. B. Russland, China",
            "description": "Lorem ipsum dolor sit amet, consetetur sadipscing elitr, sed diam nonumy eirmod tempor invidunt ut labore et dolore magna aliquyam erat, sed diam voluptua. At vero eos et accusam et",
            "storys": []
        },
        {
            "title": "Leidenschaftlich missionieren",
            "example": "z. B. Russland, China",
            "description": "Lorem ipsum dolor sit amet, consetetur sadipscing elitr, sed diam nonumy eirmod tempor invidunt ut labore et dolore magna aliquyam erat, sed diam voluptua. At vero eos et accusam et",
            "storys": []
        },
        {
            "title": "provozieren",
            "example": "z. B. Russland, China",
            "description": "Lorem ipsum dolor sit amet, consetetur sadipscing elitr, sed diam nonumy eirmod tempor invidunt ut labore et dolore magna aliquyam erat, sed diam voluptua. At vero eos et accusam et",
            "storys": []
        }
    ],
    "02": [
        {
            "title": "Mit Satiere/Parodie irritieren",
            "example": "z. B. Russland, China",
            "description": "Lorem ipsum dolor sit amet, consetetur sadipscing elitr, sed diam nonumy eirmod tempor invidunt ut labore et dolore magna aliquyam erat, sed diam voluptua. At vero eos et accusam et",
            "storys": []
        },
        {
            "title": "Ungenau/falsch betiteln, bebildern, beschriften",
            "example": "z. B. Russland, China",
            "description": "Lorem ipsum dolor sit amet, consetetur sadipscing elitr, sed diam nonumy eirmod tempor invidunt ut labore et dolore magna aliquyam erat, sed diam voluptua. At vero eos et accusam et",
            "storys": []
        },
        {
            "title": "Eine Information auf irreführende Weise nutzen (Framing)",
            "example": "z. B. Russland, China",
            "description": "Lorem ipsum dolor sit amet, consetetur sadipscing elitr, sed diam nonumy eirmod tempor invidunt ut labore et dolore magna aliquyam erat, sed diam voluptua. At vero eos et accusam et",
            "storys": []
        },
        {
            "title": "Echte Inhalte in einem falschen Kontext setzen",
            "example": "z. B. Russland, China",
            "description": "Lorem ipsum dolor sit amet, consetetur sadipscing elitr, sed diam nonumy eirmod tempor invidunt ut labore et dolore magna aliquyam erat, sed diam voluptua. At vero eos et accusam et",
            "storys": []
        },
        {
            "title": "Sich für eine andere, authentische Quelle ausgeben",
            "example": "z. B. Russland, China",
            "description": "Lorem ipsum dolor sit amet, consetetur sadipscing elitr, sed diam nonumy eirmod tempor invidunt ut labore et dolore magna aliquyam erat, sed diam voluptua. At vero eos et accusam et",
            "storys": []
        },
        {
            "title": "Inhalte gezielt manipulieren",
            "example": "z. B. Russland, China",
            "description": "Lorem ipsum dolor sit amet, consetetur sadipscing elitr, sed diam nonumy eirmod tempor invidunt ut labore et dolore magna aliquyam erat, sed diam voluptua. At vero eos et accusam et",
            "storys": []
        },
        {
            "title": "Inhalte komplett erfinden",
            "example": "z. B. Russland, China",
            "description": "Lorem ipsum dolor sit amet, consetetur sadipscing elitr, sed diam nonumy eirmod tempor invidunt ut labore et dolore magna aliquyam erat, sed diam voluptua. At vero eos et accusam et",
            "storys": []
        }
    ],
    "03": [
        {
            "title": "Marktforschung",
            "example": "z. B. Russland, China",
            "description": "Lorem ipsum dolor sit amet, consetetur sadipscing elitr, sed diam nonumy eirmod tempor invidunt ut labore et dolore magna aliquyam erat, sed diam voluptua. At vero eos et accusam et",
            "storys": []
        },
        {
            "title": "SEO-Optimierung",
            "example": "z. B. Russland, China",
            "description": "Lorem ipsum dolor sit amet, consetetur sadipscing elitr, sed diam nonumy eirmod tempor invidunt ut labore et dolore magna aliquyam erat, sed diam voluptua. At vero eos et accusam et",
            "storys": []
        },
        {
            "title": "Geo-Targeting",
            "example": "z. B. Russland, China",
            "description": "Lorem ipsum dolor sit amet, consetetur sadipscing elitr, sed diam nonumy eirmod tempor invidunt ut labore et dolore magna aliquyam erat, sed diam voluptua. At vero eos et accusam et",
            "storys": []
        },
        {
            "title": "Micro-Targeting",
            "example": "z. B. Russland, China",
            "description": "Lorem ipsum dolor sit amet, consetetur sadipscing elitr, sed diam nonumy eirmod tempor invidunt ut labore et dolore magna aliquyam erat, sed diam voluptua. At vero eos et accusam et",
            "storys": []
        },
        {
            "title": "Campaingning",
            "example": "z. B. Russland, China",
            "description": "Lorem ipsum dolor sit amet, consetetur sadipscing elitr, sed diam nonumy eirmod tempor invidunt ut labore et dolore magna aliquyam erat, sed diam voluptua. At vero eos et accusam et",
            "storys": []
        }
    ],
    "04.1": [
        {
            "title": "Geschlossende Platformen",
            "example": "z. B. Russland, China",
            "description": "Lorem ipsum dolor sit amet, consetetur sadipscing elitr, sed diam nonumy eirmod tempor invidunt ut labore et dolore magna aliquyam erat, sed diam voluptua. At vero eos et accusam et",
            "storys": []
        }
    ],
    "04A": [
        {
            "title": "Keine Kosten",
            "example": "z. B. Russland, China",
            "description": "Lorem ipsum dolor sit amet, consetetur sadipscing elitr, sed diam nonumy eirmod tempor invidunt ut labore et dolore magna aliquyam erat, sed diam voluptua. At vero eos et accusam et",
            "storys": []
        },
        {
            "title": "Hohe Performance",
            "example": "z. B. Russland, China",
            "description": "Lorem ipsum dolor sit amet, consetetur sadipscing elitr, sed diam nonumy eirmod tempor invidunt ut labore et dolore magna aliquyam erat, sed diam voluptua. At vero eos et accusam et",
            "storys": []
        },
        {
            "title": "Beliebte Funktionen",
            "example": "z. B. Russland, China",
            "description": "Lorem ipsum dolor sit amet, consetetur sadipscing elitr, sed diam nonumy eirmod tempor invidunt ut labore et dolore magna aliquyam erat, sed diam voluptua. At vero eos et accusam et",
            "storys": []
        },
        {
            "title": "Suchterzeugung",
            "example": "z. B. Russland, China",
            "description": "Lorem ipsum dolor sit amet, consetetur sadipscing elitr, sed diam nonumy eirmod tempor invidunt ut labore et dolore magna aliquyam erat, sed diam voluptua. At vero eos et accusam et",
            "storys": []
        }
    ],
    "04.2": [
        {
            "title": "Offene Platformen",
            "example": "z. B. Russland, China",
            "description": "Lorem ipsum dolor sit amet, consetetur sadipscing elitr, sed diam nonumy eirmod tempor invidunt ut labore et dolore magna aliquyam erat, sed diam voluptua. At vero eos et accusam et",
            "storys": []
        }
    ],
    "04B": [
        {
            "title": "Keine Kosten",
            "example": "z. B. Russland, China",
            "description": "Lorem ipsum dolor sit amet, consetetur sadipscing elitr, sed diam nonumy eirmod tempor invidunt ut labore et dolore magna aliquyam erat, sed diam voluptua. At vero eos et accusam et",
            "storys": []
        },
        {
            "title": "Wettbewerb um Status/Beliebtheit",
            "example": "z. B. Russland, China",
            "description": "Lorem ipsum dolor sit amet, consetetur sadipscing elitr, sed diam nonumy eirmod tempor invidunt ut labore et dolore magna aliquyam erat, sed diam voluptua. At vero eos et accusam et",
            "storys": []
        },
        {
            "title": "Wettbewerb um Aufmerksamkeit",
            "example": "z. B. Russland, China",
            "description": "Lorem ipsum dolor sit amet, consetetur sadipscing elitr, sed diam nonumy eirmod tempor invidunt ut labore et dolore magna aliquyam erat, sed diam voluptua. At vero eos et accusam et",
            "storys": []
        },
        {
            "title": "Bestätigende & radikalisierende Algorithmen/KI",
            "example": "z. B. Russland, China",
            "description": "Lorem ipsum dolor sit amet, consetetur sadipscing elitr, sed diam nonumy eirmod tempor invidunt ut labore et dolore magna aliquyam erat, sed diam voluptua. At vero eos et accusam et",
            "storys": []
        },
        {
            "title": "Suchterzeugung",
            "example": "z. B. Russland, China",
            "description": "Lorem ipsum dolor sit amet, consetetur sadipscing elitr, sed diam nonumy eirmod tempor invidunt ut labore et dolore magna aliquyam erat, sed diam voluptua. At vero eos et accusam et",
            "storys": []
        }
    ],
    "05": [
        {
            "title": "Eigene Anhänger bestärken",
            "example": "z. B. Russland, China",
            "description": "Lorem ipsum dolor sit amet, consetetur sadipscing elitr, sed diam nonumy eirmod tempor invidunt ut labore et dolore magna aliquyam erat, sed diam voluptua. At vero eos et accusam et",
            "storys": []
        },
        {
            "title": "Neutrales, noch unentschlossenes Lager überzeugen",
            "example": "z. B. Russland, China",
            "description": "Lorem ipsum dolor sit amet, consetetur sadipscing elitr, sed diam nonumy eirmod tempor invidunt ut labore et dolore magna aliquyam erat, sed diam voluptua. At vero eos et accusam et",
            "storys": []
        },
        {
            "title": "Entgegengesetztes Lager verunsichern, provozieren, polarisieren",
            "example": "z. B. Russland, China",
            "description": "Lorem ipsum dolor sit amet, consetetur sadipscing elitr, sed diam nonumy eirmod tempor invidunt ut labore et dolore magna aliquyam erat, sed diam voluptua. At vero eos et accusam et",
            "storys": []
        },
        {
            "title": "Entgegengesetzte Lager gegeneinander aufhetzen",
            "example": "z. B. Russland, China",
            "description": "Lorem ipsum dolor sit amet, consetetur sadipscing elitr, sed diam nonumy eirmod tempor invidunt ut labore et dolore magna aliquyam erat, sed diam voluptua. At vero eos et accusam et",
            "storys": []
        }
    ]
}